froster_publish_pypi
