Metadata-Version: 2.1
Name: froster-publish-pypi
Version: 0.5.0
Summary: UNKNOWN
Home-page: UNKNOWN
License: UNKNOWN
Platform: UNKNOWN
